{
  "date": "2026-06-29",
  "generated_at": "2026-06-29T11:08:00+08:00",
  "source": "analyst-assemble",
  "input_files": {
    "brief": ".analyst-brief-2026-06-29.json (8 signals, all fire)",
    "verify": ".analyst-verify-2026-06-29.json (5 verified: 2 triple, 1 dual, 2 single)",
    "funds": ".analyst-funds-2026-06-29.json (data_date: 20260627, 511 anomalies, 146 up/363 down)"
  },

  "signal_analysis": [
    {
      "id": "s1",
      "title": "长鑫存储295亿IPO在即，DRAM国产化从概念进入兑现期",
      "priority": "fire",
      "chain": "chain1",
      "verify_confidence": "triple (凤凰/钛媒体/新浪/ZAKER 4家独立信源)",
      "question_variable": "证监会同意科创板IPO注册→长鑫从fabless进入IDM模式的核心变量",
      "question_magnitude": "295亿元募资=科创板史上第二大IPO。2026Q1营收508亿元，DDR5/LPDDR5规模化量产+HBM3研发，长江存储IPO同步提速。量级极高",
      "question_persistence": "持久。DDR5/HBM二期扩产为2-3年资本开支周期，国产化不可逆。但需注意HBM3仍处研发阶段而非量产，产能爬坡需时间验证",
      "pricing": "under_priced",
      "pricing_rationale": "triple verified但资金仅通过上游硅片/材料间接定价(有研硅+20%、上海合晶+15.99%)。兆易创新/江波龙等长鑫IPO直接映射标的未动。长鑫IPO自身映射(兆易创新参股长鑫/江波龙战略合作)尚未定价",
      "funding": "strong",
      "funding_rationale": "半导体材料板块avg +3.53%(23/25联动)，有研硅+20%涨停vol 7.47(增量机构资金)。资金通过硅片/材料端表达对长鑫扩产的认可，路径明确"
    },
    {
      "id": "s2",
      "title": "中国2950亿美元国产AI芯片强制令：华为昇腾2026 AI收入120亿美元(+60%)",
      "priority": "fire",
      "chain": "chain2",
      "verify_confidence": "single (国产AI芯片替代大方向确认，但2950亿/120亿美元具体数字未独立验证)",
      "question_variable": "国家发改委AI数据中心国产芯片强制令落地",
      "question_magnitude": "总额2950亿美元。华为昇腾120亿美元AI收入=同比+60%。量级极大(>美国AI芯片禁令总额)",
      "question_persistence": "政策强制+5年周期，技术锁定的不可逆性。但华为非上市无法直接交易，寒武纪/海光营收体量仍小(海光2025营收约60亿人民币)，业绩兑现需1-2年",
      "pricing": "under_priced",
      "pricing_rationale": "⚠️ 带条件：政策大方向正确但核心定量数据未经独立验证(single confidence)。AI算力板块avg -5.99%显示资金全面否定此叙事。若政策数字后续验证为真(如权威媒体确认)，则背离规模为本周最大级别",
      "funding": "weak",
      "funding_rationale": "AI算力标签板块avg -5.99%居全市场跌幅第二(仅次于生物医药)。寒武纪/海光/沐曦0进榜。最严重的信号-资金背离"
    },
    {
      "id": "s3",
      "title": "高盛：超大规模CSP资本开支2026年可能超全球半导体行业总收入",
      "priority": "fire",
      "chain": "chain2",
      "verify_confidence": "single (高盛确实谈论5.3万亿AI资本开支，但'CSP capex匹敌5270亿美元半导体总收入'这一具体对比论断未出现)",
      "question_variable": "高盛判断AI基建成为独立于周期的超级需求引擎",
      "question_magnitude": "CSP资本开支单年度可能匹敌全球半导体行业总收入(~5270亿美元)。量级极为震撼",
      "question_persistence": "CSP资本开支为多年持续投入。但市场对AI宏大叙事已有审美疲劳——同样的话从2024讲到2026",
      "pricing": "under_priced",
      "pricing_rationale": "光通信-4.77%(长盈通/长光华芯/仕佳光子三只超-10%)。CSP资本开支的宏大叙事无法阻止光通信板块系统性杀跌。但verify信心仅single——若该论断是引用偏差而非高盛原意，则背离实际不存在",
      "funding": "weak",
      "funding_rationale": "光通信-4.77%系统性下跌。信号-资金背离。需区分：可能不是资金不认可AI基建逻辑，而是当前阶段资金偏好从'预期叙事'转向'订单验证'"
    },
    {
      "id": "s4",
      "title": "存储芯片超级涨价周期：Q1 DRAM合约价+83-90%，DDR5从$5.5飙至$40+",
      "priority": "fire",
      "chain": "chain1",
      "verify_confidence": "triple (TrendForce+36氪+SoftwareSeni+东方财富4源确认。Q1涨幅83-95%区间一致。DDR5 $5.5→$40+具体报价未复现但量级吻合)",
      "question_variable": "AI HBM挤占通用DRAM产能导致供给严重紧缩",
      "question_magnitude": "Q1 DRAM合约价+83-95%=有记录以来最大季度涨幅。DDR5一年+600%。苹果吃不消涨价寻求中国芯片。量级历史级别",
      "question_persistence": "HBM挤占产能为结构性而非周期性，可持续数年。但Goldman预测Q3仅+13%——涨价斜率正在放缓。需警惕Q2可能是涨价顶峰",
      "pricing": "partially_priced",
      "pricing_rationale": "triple verified最强事实数据，但存储设计标的(兆易创新/佰维存储/江波龙/德明利/东芯股份)0进异动榜。涨价逻辑被资金绕行至上游制造端(有研硅+20%/正帆科技+20%)。市场定价路径：'涨价→晶圆厂扩产→上游材料/设备'而非'涨价→设计公司利润暴增'。苹果吃不消涨价寻求替代是市场担心设计端传导能力的隐忧",
      "funding": "moderate",
      "funding_rationale": "上游制造端资金强劲(半导体材料+3.53%/零部件+6.97%)但存储设计端零响应。资金选择路径偏移而非不认可涨价逻辑"
    },
    {
      "id": "s7",
      "title": "半导体设备国产化率2026集中兑现，长鑫供应链国产设备占比40-50%",
      "priority": "fire",
      "chain": "chain1",
      "verify_confidence": "dual (国产替代趋势多源确认，整体国产化率24%/刻蚀31%。但'长鑫供应链40-50%'具体数字未直接复现——可能指特定产线而非全供应链。Q2净利30-50%未单独验证)",
      "question_variable": "海外设备交期延长至半年以上倒逼国产替代+长鑫/长存扩产拉动",
      "question_magnitude": "北方华创/中微Q2净利30-50%。长鑫供应链国产设备占比从13%→40-50%。量级高",
      "question_persistence": "3年黄金渗透周期。设备国产化是2-3年结构性趋势，订单排产至2027Q3(Triple验证)。持续性最强",
      "pricing": "partially_priced",
      "pricing_rationale": "正帆科技连续两日+20%涨停(vol 8.13最强)、富创精密+20%涨停、新莱应材+14.54%。半导体零部件+6.97%全市场最强。但北方华创/中微/拓荆/盛美上海等大市值龙头未涨停——小票先行龙头滞后。设备链定价效应偏斜(弹性小市值>确定性大市值)",
      "funding": "strong",
      "funding_rationale": "本周最强资金验证信号。正帆科技vol 8.13全榜最高(连续两日+20%)、零部件板块avg +6.97%全市场第一、sum_pct 90.59。增量机构资金持续涌入。但龙头滞后可能导致后续拉回或补涨"
    },
    {
      "id": "rs1",
      "title": "具身智能「卖不动、租得火」：租赁被定义为唯一规模化盈利路径，市场规模10倍跳变",
      "priority": "fire",
      "chain": "robot",
      "verify_confidence": "N/A (robot-scanner原创分析，未提交verify)",
      "question_variable": "商业模式从卖硬件→租服务切换",
      "question_magnitude": "租赁市场10亿→100亿(10倍)，但日租金从1-3万跌至千元区间(-60~-90%)，场景仅商场开业/年会表演引流。利好多空双向极大量级对冲",
      "question_persistence": "缺乏重复性刚需。当前仅表演引流场景，工业制造/物流/家政等重复性场景尚未打开",
      "pricing": "under_priced",
      "pricing_rationale": "复杂多空交织信号未被定价。机器人板块avg -2.75%，5只related标的0进榜。市场需要更多证据来确定租赁模式是方向性利好(验证有需求)还是伪需求(只是表演噱头)",
      "funding": "weak",
      "funding_rationale": "机器人板块连续数周零响应(系统纪录：信号密度>30条vs异动0只)"
    },
    {
      "id": "rs2",
      "title": "人形机器人关键零部件成本降速量化：六维力传感器降>60%，3D相机降70%，一体化关节年降10-15%",
      "priority": "fire",
      "chain": "robot",
      "verify_confidence": "N/A (robot-scanner原创分析)",
      "question_variable": "构型收敛+良率提升(85%→98%)+月产能万台级驱动成本加速下降",
      "question_magnitude": "六维力2-3万→5000-8000元(-60%+)，3D相机降70%，远超此前市场预期5-8%。量级大",
      "question_persistence": "成本下降趋势持续但分阶段性：当前构型收敛+良率提升驱动，下一步需规模效应。但灵巧手'不可能三角'(精密装配反规模经济)将限制部分环节降速",
      "pricing": "under_priced",
      "pricing_rationale": "成本降速远超预期但资金未定价。注意双刃剑效应：对整机厂是利好(降本加速商业化)，对零部件供应商是利空(价格下行利润挤压)。但686只A股机器人标的中以零部件为主而非整机厂，市场可能将此解读为利空信号",
      "funding": "weak",
      "funding_rationale": "机器人板块零响应。成本降速的产业意义>短期股价影响"
    },
    {
      "id": "rs4",
      "title": "具身智能相关企业突破万家，但约8成仅停留在平台搭建阶段——行业出清窗口已具三重证据",
      "priority": "fire",
      "chain": "robot",
      "verify_confidence": "N/A (robot-scanner原创分析，但引用中工网+钛媒体)",
      "question_variable": "万家注册企业+8成PPT+融资马太(27家卷走全部)+30-40%库存→行业出清确认",
      "question_magnitude": "行业6-12个月出清窗口，真正量产<30家(~0.3%)。对龙头利好(份额提升)，对非龙头利空(融资枯竭)。量级中高",
      "question_persistence": "出清过程一旦开启将持续至行业格局稳定(6-12个月)。出清后的竞争格局改善是长期利好",
      "pricing": "under_priced",
      "pricing_rationale": "双重未定价：龙头利好(绿的谐波/汇川/三花通过出清获更高份额)vs非龙头风险均未被市场讨论。在当前复杂信号环境中，市场选择完全不碰机器人方向",
      "funding": "weak",
      "funding_rationale": "零资金响应。三条机器人fire信号连续数周无法获得任何资金响应"
    }
  ],

  "divergences": {
    "total": 5,
    "critical": 1,
    "high": 2,
    "medium": 2,

    "critical_list": [
      {
        "id": "div_c1",
        "type": "signal_vs_funds",
        "severity": "critical",
        "description": "s2(AI芯片2950亿美元强制令fire) vs AI算力板块-5.99%：最强政策催化被最强资金否定",
        "details": "2950亿美元强制令+华为昇腾120亿美元收入(+60%)是本周最强政策催化。但AI算力标签板块avg -5.99%居全市场跌幅第二(仅低于生物医药-10.63%)。5只related AI芯片标的无1进异动榜。寒武纪/海光信息/沐曦全面下跌。这是今日最严重的信号-资金背离——在半导体链全面涨停背景下，AI政策受益方向反而成为资金流出方向。",
        "resolution_observation": "当前盘面为6/27(周五)数据。周一(6/29)观察该方向是否续跌。若续跌确认短期见顶。若企稳反弹则背离部分修复。但若政策数字(2950亿)后续被权威媒体独立验证，背离级别将升格为'系统层面定价错误'"
      }
    ],

    "high_list": [
      {
        "id": "div_h1",
        "type": "signal_vs_funds",
        "severity": "high",
        "description": "s3(高盛CSP capex>全球半导体总收入fire) vs 光通信-4.77%：宏大叙事被资金反向交易",
        "details": "CSP资本开支匹敌5270亿美元的量级判断极为震撼。但光通信与光学板块avg -4.77%，长盈通/长光华芯/仕佳光子三只跌超-10%。中际旭创/新易盛/工业富联等AI算力传统龙头未进异动榜(下跌但未触发异动阈值)。",
        "resolution_observation": "verify仅single——关键对比论断(5270亿对比)是否真是高盛原话存疑。若后续验证为引用偏差，此背离实际不成立。市场当前无论该论断真伪一律选择不买账"
      },
      {
        "id": "div_h2",
        "type": "signal_density_vs_response",
        "severity": "high",
        "description": "机器人3条fire(rs1+rs2+rs4)连续数周零资金响应——信号密度vs资金响应背离创系统纪录",
        "details": "rs1(租赁10倍/租金暴跌90%)、rs2(零部件成本降速远超预期)、rs4(三重证据出清窗口)——三条独立方向的fire信号，combined信号密度本周>30条。但机器人板块avg -2.75%，5只related标的(688017/002472/300124/002050/601689)无一进入异动涨榜。背离已持续3周以上，创系统运行以来最长纪录。",
        "resolution_observation": "背离突破机制：(1)半导体热度降温后资金可能轮动至机器人；(2)V3亮相或京东涅槃订单为强催化剂。但当前市场聚焦半导体制造端一条主线，其他方向全线被忽视"
      }
    ],

    "medium_list": [
      {
        "id": "div_m1",
        "type": "pricing_path_bias",
        "severity": "medium",
        "description": "s4(存储涨价triple verified)逻辑绕行设计端→制造端，定价路径偏移",
        "details": "Q1 DRAM合约价+83-95%(有记录以来最大涨幅)、DDR5一年+600%。但5只存储设计/模组标的兆易创新/佰维存储/江波龙/德明利/东芯股份0进异动榜。涨价逻辑被资金绕过了芯片设计端，直接流向硅片(有研硅+20%)和设备零部件(正帆科技+20%)。市场定价路径：'涨价→晶圆厂扩产→设备/材料需求'。苹果吃不消涨价寻求中国芯片替代是市场担心设计端传导能力的关键隐忧。",
        "resolution_observation": "DRAM涨价Q3仅+13%(Goldman预测)意味着Q2可能是涨价顶峰。若后续DRAM现货价松动，存储设计端的补涨窗口可能关闭"
      },
      {
        "id": "div_m2",
        "type": "pricing_hierarchy",
        "severity": "medium",
        "description": "s7(设备国产化率40-50%)小票涨停潮vs龙头严重滞后，定价效应偏斜",
        "details": "正帆科技+20%连续两天涨停、富创精密+20%、新莱应材+14.54%——零部件小票全面涨停。但北方华创/中微公司两大设备龙头未进异动榜(分别+9%/+8%左右但未达20%门槛)。设备链的定价效应偏斜：弹性小市值>确定性大市值。",
        "resolution_observation": "周一(6/29)北方华创/中微走势决定此背离方向：(1)龙头补涨→背离修复、主线确认；(2)龙头继续滞后→背离升级至high，市场可能担心龙头估值偏高或逻辑不纯"
      }
    ]
  },

  "core_narrative": "市场从'叙事驱动'阶段进入'订单验证'阶段。半导体制造端(设备/材料/零部件)有长鑫295亿IPO+设备国产化率40-50%+Q2净利30-50%三重即期订单验证，获得真金白银涌入。半导体零部件avg +6.97%全市场最强、材料+3.53%联动率92%、设备+1.60%温和走强。AI芯片/光通信仅有远期叙事而无即期业绩——AI芯片强制令(s2 fire级)下AI算力反跌-5.99%、高盛AI capex(s3 fire级)下光通信跌-4.77%。机器人方向信号复杂多空交织(租赁利好vs租金利空/降本利好整机vs利空零部件/出清利好龙头vs短期杀估值)，连续数周零资金响应。正帆科技连续两日+20%涨停(vol 8.13全榜最高)是当前市场'有订单的制造'>'有叙事的预期'偏好的完美例证。⚠️ 若s2(AI芯片强制令)的核心数字(2950亿/120亿美元)后续被权威媒体验证为真而非引用偏差，则今日AI算力-5.99%将成为系统级别最大的定价错误——但当前数据尚不支持此结论，需持续关注。",

  "capital_path": "半导体零部件(avg +6.97%) >> 半导体材料(avg +3.53%) > 半导体设备(avg +1.60%) > 工业设备(avg -1.50%) > IC设计(avg -2.0%) > 机器人(avg -2.75%) > 消费电子(avg -3.88%) > 新能源(avg -4.55%) > 封测/光通信/通信(avg -4.77%) > 软件IT(avg -5.01%) > AI算力(avg -5.99%) > 生物医药(avg -10.63%)",

  "core_verdict": "市场聚焦一条主线(半导体制造端)全面走强；AI芯片/光通信天大利好反跌(信号-资金背离)；机器人方向信号密暴但0资金响应；新能源/医药持续失血。分化逻辑：'有即期订单+国产替代+扩产逻辑的涨，有宏大叙事但无即期业绩的跌，无催化的持续跌。'",

  "strongly_verified_signals": ["s7(设备国产化率40-50%→正帆科技连续涨停)", "s1(长鑫295亿IPO→有研硅/上海合晶涨停)"],
  "partially_verified_signals": ["s4(存储涨价→资金绕行制造端)"],
  "disconfirmed_signals": ["s2(AI芯片强制令→AI算力-5.99%背离)", "s3(高盛AI capex→光通信-4.77%背离)", "rs1+rs2+rs4(机器人3条fire→0资金响应)"],

  "pricing_summary": {
    "under_priced": [
      "s2(AI芯片强制令): 政策方向正确但核心数字未独立验证。AI算力板块全面下跌尚未定价",
      "s3(高盛CSP capex): 宏大叙事被资金反向交易。但verify信心弱",
      "rs1(租赁10倍): 复杂多空信号未被定价",
      "rs2(零部件降本): 成本加速降速的产业意义>股价影响",
      "rs4(出清窗口): 龙头利好+非龙头风险双重未定价",
      "s1(长鑫IPO): 仅间接定价硅片端，直接映射标的未动"
    ],
    "partially_priced": [
      "s4(存储涨价): 涨价逻辑绕行至制造端定价，设计端未定价",
      "s7(设备国产化): 小票涨停但龙头滞后"
    ],
    "fully_priced": []
  },

  "funding_summary": {
    "strong": ["s7(设备国产化: 正帆科技vol 8.13连续涨停)", "s1(长鑫IPO: 有研硅vol 7.47涨停)"],
    "moderate": ["s4(存储涨价: 上游制造端强劲但设计端零响应)"],
    "weak": [
      "s2(AI芯片强制令: AI算力-5.99%全线下跌)",
      "s3(高盛AI capex: 光通信-4.77%系统性杀跌)",
      "rs1(租赁: 机器人-2.75%零响应)",
      "rs2(零部件降本: 机器人零响应)",
      "rs4(出清窗口: 机器人零响应)"
    ]
  },

  "most_under_priced": "rs2(零部件成本降速远超预期) >> s1(长鑫IPO直接映射) >> rs1(租赁10倍信号) >= rs4(出清窗口)",

  "risk_warnings": [
    "🔴 CRITICAL: s2 AI芯片强制令(single verify)+AI算力-5.99%是本日最大背离。若政策数字后续被验证为真，背离规模系统级",
    "🔴 6/27(周五)呈现363跌/146涨熊市底色，仅半导体链走强。若周一(6/29)半导体热度消退但无新主线接力，大盘整体承压",
    "🔴 数据时效性：funds分析基于6/27(周五)数据，今日6/29(周一)盘中可能已发生变化",
    "🟡 s2关键数字2950亿/120亿美元仅single verify——政策基调和金额偏差风险",
    "🟡 s3高盛CSP对比论断(single verify)——若为引用偏差则背离不成立",
    "🟡 s7设备链龙头(北方华创/中微)严重滞后——周一走势是主线确认或证伪关键窗口",
    "🟡 s4存储涨价Q3仅+13%(Goldman)——Q2可能是涨价顶峰，后续涨价斜率放缓风险已被部分定价",
    "🟡 rs2双刃剑效应：零部件成本降速对整机厂利好但对A股零部件标的利空",
    "🟡 机器人方向连续数周零资金响应——信号密度与资金响应背离极端化"
  ]
}
