{
  "generated_at": "2026-05-28T16:52:44.861668",
  "week_date": "20260528",
  "filter": "J<15 + 白线>黄线",
  "summary": {
    "golden": 73,
    "weekly_only": 47,
    "missed": 6,
    "weak_filtered": 56
  },
  "clusters": {
    "生物医药": 28,
    "新能源(光风储电)": 18,
    "商业航天与低空": 12,
    "生物医药与器械": 11,
    "国产软件与信创": 10,
    "核电": 6,
    "化工/材料": 4,
    "量子信息": 4,
    "新材料": 3,
    "氢能": 3,
    "新能源/电力设备": 3,
    "未分类": 3
  },
  "golden": [
    {
      "ts_code": "688331.SH",
      "name": "荣昌生物",
      "theme_category": "生物医药与器械",
      "week": "2026-W22",
      "week_date": "20260528",
      "week_J": -64.83,
      "week_K": -11.65,
      "week_D": 14.94,
      "white_line": 112.1,
      "yellow_line": 90.33,
      "day_J": 8.0,
      "day_date": "20260528",
      "trend_ok": true,
      "backtest_win_rate": 100.0,
      "backtest_avg_return": 138.18,
      "backtest_trades": 1
    },
    {
      "ts_code": "002074.SZ",
      "name": "国轩高科",
      "theme_category": "新能源(光风储电)",
      "week": "2026-W22",
      "week_date": "20260527",
      "week_J": -28.86,
      "week_K": -64.47,
      "week_D": -82.28,
      "white_line": 36.32,
      "yellow_line": 33.5,
      "day_J": 6.34,
      "day_date": "20260527",
      "trend_ok": true,
      "backtest_win_rate": 100.0,
      "backtest_avg_return": 119.93,
      "backtest_trades": 1
    },
    {
      "ts_code": "300436.SZ",
      "name": "广生堂",
      "theme_category": "生物医药",
      "week": "2026-W22",
      "week_date": "20260528",
      "week_J": -423.85,
      "week_K": -165.9,
      "week_D": -36.92,
      "white_line": 105.07,
      "yellow_line": 86.95,
      "day_J": -8.99,
      "day_date": "20260528",
      "trend_ok": true,
      "backtest_win_rate": 100.0,
      "backtest_avg_return": 119.03,
      "backtest_trades": 1
    },
    {
      "ts_code": "600879.SH",
      "name": "航天电子",
      "theme_category": "商业航天与低空",
      "week": "2026-W22",
      "week_date": "20260528",
      "week_J": -21.09,
      "week_K": -3.22,
      "week_D": 5.71,
      "white_line": 21.64,
      "yellow_line": 17.06,
      "day_J": 7.22,
      "day_date": "20260528",
      "trend_ok": true,
      "backtest_win_rate": 100.0,
      "backtest_avg_return": 114.1,
      "backtest_trades": 1
    },
    {
      "ts_code": "002361.SZ",
      "name": "神剑股份",
      "theme_category": "化工/材料",
      "week": "2026-W22",
      "week_date": "20260527",
      "week_J": -22.82,
      "week_K": 23.16,
      "week_D": 46.15,
      "white_line": 14.59,
      "yellow_line": 10.83,
      "day_J": 4.57,
      "day_date": "20260527",
      "trend_ok": true,
      "backtest_win_rate": 100.0,
      "backtest_avg_return": 107.4,
      "backtest_trades": 1
    },
    {
      "ts_code": "002009.SZ",
      "name": "天奇股份",
      "theme_category": "具身智能/机器人",
      "week": "2026-W22",
      "week_date": "20260527",
      "week_J": -3.44,
      "week_K": 1.52,
      "week_D": 4.0,
      "white_line": 23.8,
      "yellow_line": 20.38,
      "day_J": -13.53,
      "day_date": "20260527",
      "trend_ok": true,
      "backtest_win_rate": 100.0,
      "backtest_avg_return": 98.74,
      "backtest_trades": 1
    },
    {
      "ts_code": "000703.SZ",
      "name": "恒逸石化",
      "theme_category": "化工/材料",
      "week": "2026-W22",
      "week_date": "20260527",
      "week_J": 3.05,
      "week_K": 21.01,
      "week_D": 29.99,
      "white_line": 12.51,
      "yellow_line": 9.99,
      "day_J": 12.98,
      "day_date": "20260527",
      "trend_ok": true,
      "backtest_win_rate": 100.0,
      "backtest_avg_return": 83.79,
      "backtest_trades": 1
    },
    {
      "ts_code": "301005.SZ",
      "name": "超捷股份",
      "theme_category": "汽车零部件",
      "week": "2026-W22",
      "week_date": "20260528",
      "week_J": -7.9,
      "week_K": 13.13,
      "week_D": 23.65,
      "white_line": 148.03,
      "yellow_line": 106.32,
      "day_J": 11.04,
      "day_date": "20260528",
      "trend_ok": true,
      "backtest_win_rate": 100.0,
      "backtest_avg_return": 68.24,
      "backtest_trades": 1
    },
    {
      "ts_code": "002455.SZ",
      "name": "百川股份",
      "theme_category": "新能源(光风储电)",
      "week": "2026-W22",
      "week_date": "20260527",
      "week_J": -27.91,
      "week_K": -14.06,
      "week_D": -7.13,
      "white_line": 10.41,
      "yellow_line": 9.12,
      "day_J": 4.29,
      "day_date": "20260527",
      "trend_ok": true,
      "backtest_win_rate": 100.0,
      "backtest_avg_return": 66.52,
      "backtest_trades": 1
    },
    {
      "ts_code": "688063.SH",
      "name": "XD派能科",
      "theme_category": "新能源(光风储电)",
      "week": "2026-W22",
      "week_date": "20260528",
      "week_J": -62.9,
      "week_K": -20.56,
      "week_D": 0.61,
      "white_line": 67.81,
      "yellow_line": 59.67,
      "day_J": 1.37,
      "day_date": "20260528",
      "trend_ok": true,
      "backtest_win_rate": 100.0,
      "backtest_avg_return": 46.84,
      "backtest_trades": 1
    },
    {
      "ts_code": "600343.SH",
      "name": "航天动力",
      "theme_category": "商业航天与低空",
      "week": "2026-W22",
      "week_date": "20260528",
      "week_J": -65.31,
      "week_K": -20.18,
      "week_D": 2.39,
      "white_line": 31.62,
      "yellow_line": 24.88,
      "day_J": -1.67,
      "day_date": "20260528",
      "trend_ok": true,
      "backtest_win_rate": 100.0,
      "backtest_avg_return": 43.62,
      "backtest_trades": 1
    },
    {
      "ts_code": "601698.SH",
      "name": "中国卫通",
      "theme_category": "商业航天与低空",
      "week": "2026-W22",
      "week_date": "20260528",
      "week_J": -18.72,
      "week_K": 5.13,
      "week_D": 17.06,
      "white_line": 32.87,
      "yellow_line": 27.65,
      "day_J": 10.04,
      "day_date": "20260528",
      "trend_ok": true,
      "backtest_win_rate": 100.0,
      "backtest_avg_return": 43.34,
      "backtest_trades": 1
    },
    {
      "ts_code": "003009.SZ",
      "name": "中天火箭",
      "theme_category": "商业航天与低空",
      "week": "2026-W22",
      "week_date": "20260528",
      "week_J": -53.77,
      "week_K": -24.97,
      "week_D": -10.58,
      "white_line": 59.08,
      "yellow_line": 53.88,
      "day_J": 6.13,
      "day_date": "20260528",
      "trend_ok": true,
      "backtest_win_rate": 100.0,
      "backtest_avg_return": 42.8,
      "backtest_trades": 1
    },
    {
      "ts_code": "002460.SZ",
      "name": "赣锋锂业",
      "theme_category": "新能源(光风储电)",
      "week": "2026-W22",
      "week_date": "20260527",
      "week_J": -48.11,
      "week_K": 1.57,
      "week_D": 26.41,
      "white_line": 72.32,
      "yellow_line": 59.64,
      "day_J": 8.43,
      "day_date": "20260527",
      "trend_ok": true,
      "backtest_win_rate": 100.0,
      "backtest_avg_return": 40.72,
      "backtest_trades": 1
    },
    {
      "ts_code": "603496.SH",
      "name": "恒为科技",
      "theme_category": "具身智能/机器人",
      "week": "2026-W22",
      "week_date": "20260528",
      "week_J": -169.47,
      "week_K": -85.04,
      "week_D": -42.82,
      "white_line": 28.32,
      "yellow_line": 27.32,
      "day_J": -0.66,
      "day_date": "20260528",
      "trend_ok": true,
      "backtest_win_rate": 100.0,
      "backtest_avg_return": 38.59,
      "backtest_trades": 1
    },
    {
      "ts_code": "002923.SZ",
      "name": "润都股份",
      "theme_category": "生物医药",
      "week": "2026-W22",
      "week_date": "20260528",
      "week_J": -33.09,
      "week_K": -22.18,
      "week_D": -16.73,
      "white_line": 13.24,
      "yellow_line": 12.69,
      "day_J": 5.88,
      "day_date": "20260528",
      "trend_ok": true,
      "backtest_win_rate": 100.0,
      "backtest_avg_return": 35.53,
      "backtest_trades": 1
    },
    {
      "ts_code": "688375.SH",
      "name": "国博电子",
      "theme_category": "国产软件与信创",
      "week": "2026-W22",
      "week_date": "20260528",
      "week_J": -42.9,
      "week_K": -19.55,
      "week_D": -7.88,
      "white_line": 106.91,
      "yellow_line": 87.26,
      "day_J": 6.23,
      "day_date": "20260528",
      "trend_ok": true,
      "backtest_win_rate": 100.0,
      "backtest_avg_return": 33.38,
      "backtest_trades": 1
    },
    {
      "ts_code": "002446.SZ",
      "name": "盛路通信",
      "theme_category": "国产软件与信创",
      "week": "2026-W22",
      "week_date": "20260527",
      "week_J": -9.0,
      "week_K": 1.54,
      "week_D": 6.81,
      "white_line": 9.93,
      "yellow_line": 8.89,
      "day_J": 2.66,
      "day_date": "20260527",
      "trend_ok": true,
      "backtest_win_rate": 100.0,
      "backtest_avg_return": 33.29,
      "backtest_trades": 1
    },
    {
      "ts_code": "300699.SZ",
      "name": "光威复材",
      "theme_category": "新材料",
      "week": "2026-W22",
      "week_date": "20260528",
      "week_J": -73.86,
      "week_K": -40.68,
      "week_D": -24.09,
      "white_line": 33.93,
      "yellow_line": 32.27,
      "day_J": 13.56,
      "day_date": "20260528",
      "trend_ok": true,
      "backtest_win_rate": 100.0,
      "backtest_avg_return": 32.42,
      "backtest_trades": 1
    },
    {
      "ts_code": "300725.SZ",
      "name": "药石科技",
      "theme_category": "生物医药",
      "week": "2026-W22",
      "week_date": "20260528",
      "week_J": -80.41,
      "week_K": -17.49,
      "week_D": 13.97,
      "white_line": 37.46,
      "yellow_line": 36.74,
      "day_J": 14.84,
      "day_date": "20260528",
      "trend_ok": true,
      "backtest_win_rate": 100.0,
      "backtest_avg_return": 32.42,
      "backtest_trades": 1
    },
    {
      "ts_code": "600118.SH",
      "name": "中国卫星",
      "theme_category": "低空经济/航空",
      "week": "2026-W22",
      "week_date": "20260528",
      "week_J": 10.29,
      "week_K": 22.06,
      "week_D": 27.94,
      "white_line": 82.98,
      "yellow_line": 63.08,
      "day_J": 4.69,
      "day_date": "20260528",
      "trend_ok": true,
      "backtest_win_rate": 100.0,
      "backtest_avg_return": 30.69,
      "backtest_trades": 1
    },
    {
      "ts_code": "600860.SH",
      "name": "京城股份",
      "theme_category": "氢能",
      "week": "2026-W22",
      "week_date": "20260528",
      "week_J": -102.08,
      "week_K": -57.6,
      "week_D": -35.36,
      "white_line": 11.44,
      "yellow_line": 11.38,
      "day_J": 1.38,
      "day_date": "20260528",
      "trend_ok": true,
      "backtest_win_rate": 100.0,
      "backtest_avg_return": 29.29,
      "backtest_trades": 1
    },
    {
      "ts_code": "002340.SZ",
      "name": "格林美",
      "theme_category": "新能源(光风储电)",
      "week": "2026-W22",
      "week_date": "20260527",
      "week_J": 5.93,
      "week_K": 11.98,
      "week_D": 15.01,
      "white_line": 8.22,
      "yellow_line": 7.66,
      "day_J": 13.4,
      "day_date": "20260527",
      "trend_ok": true,
      "backtest_win_rate": 100.0,
      "backtest_avg_return": 27.95,
      "backtest_trades": 1
    },
    {
      "ts_code": "603127.SH",
      "name": "昭衍新药",
      "theme_category": "生物医药",
      "week": "2026-W22",
      "week_date": "20260528",
      "week_J": -24.59,
      "week_K": 22.35,
      "week_D": 45.82,
      "white_line": 34.15,
      "yellow_line": 29.79,
      "day_J": 14.13,
      "day_date": "20260528",
      "trend_ok": true,
      "backtest_win_rate": 100.0,
      "backtest_avg_return": 27.26,
      "backtest_trades": 3
    },
    {
      "ts_code": "002268.SZ",
      "name": "电科网安",
      "theme_category": "量子信息",
      "week": "2026-W22",
      "week_date": "20260527",
      "week_J": -86.2,
      "week_K": -51.68,
      "week_D": -34.42,
      "white_line": 16.89,
      "yellow_line": 16.88,
      "day_J": -0.49,
      "day_date": "20260527",
      "trend_ok": true,
      "backtest_win_rate": 100.0,
      "backtest_avg_return": 25.8,
      "backtest_trades": 1
    },
    {
      "ts_code": "002326.SZ",
      "name": "永太科技",
      "theme_category": "新能源(光风储电)",
      "week": "2026-W22",
      "week_date": "20260527",
      "week_J": -94.27,
      "week_K": -52.68,
      "week_D": -31.88,
      "white_line": 22.66,
      "yellow_line": 19.18,
      "day_J": 4.9,
      "day_date": "20260527",
      "trend_ok": true,
      "backtest_win_rate": 100.0,
      "backtest_avg_return": 25.53,
      "backtest_trades": 1
    },
    {
      "ts_code": "688428.SH",
      "name": "诺诚健华",
      "theme_category": "生物医药与器械",
      "week": "2026-W22",
      "week_date": "20260528",
      "week_J": -49.53,
      "week_K": -3.01,
      "week_D": 20.26,
      "white_line": 24.46,
      "yellow_line": 22.34,
      "day_J": 14.35,
      "day_date": "20260528",
      "trend_ok": true,
      "backtest_win_rate": 100.0,
      "backtest_avg_return": 20.96,
      "backtest_trades": 1
    },
    {
      "ts_code": "300720.SZ",
      "name": "海川智能",
      "theme_category": "工业设备/通用机械",
      "week": "2026-W22",
      "week_date": "20260528",
      "week_J": -44.06,
      "week_K": 9.3,
      "week_D": 35.98,
      "white_line": 49.09,
      "yellow_line": 37.26,
      "day_J": 8.78,
      "day_date": "20260528",
      "trend_ok": true,
      "backtest_win_rate": 100.0,
      "backtest_avg_return": 20.21,
      "backtest_trades": 1
    },
    {
      "ts_code": "600498.SH",
      "name": "烽火通信",
      "theme_category": "国产软件与信创",
      "week": "2026-W22",
      "week_date": "20260528",
      "week_J": -20.28,
      "week_K": 3.95,
      "week_D": 16.06,
      "white_line": 44.63,
      "yellow_line": 35.2,
      "day_J": 1.19,
      "day_date": "20260528",
      "trend_ok": true,
      "backtest_win_rate": 100.0,
      "backtest_avg_return": 16.49,
      "backtest_trades": 2
    },
    {
      "ts_code": "002318.SZ",
      "name": "久立特材",
      "theme_category": "核电",
      "week": "2026-W22",
      "week_date": "20260527",
      "week_J": -77.26,
      "week_K": -54.86,
      "week_D": -43.67,
      "white_line": 27.78,
      "yellow_line": 25.65,
      "day_J": 4.95,
      "day_date": "20260527",
      "trend_ok": true,
      "backtest_win_rate": 100.0,
      "backtest_avg_return": 15.5,
      "backtest_trades": 2
    },
    {
      "ts_code": "688180.SH",
      "name": "君实生物-U",
      "theme_category": "生物医药",
      "week": "2026-W22",
      "week_date": "20260528",
      "week_J": -34.96,
      "week_K": 7.61,
      "week_D": 28.9,
      "white_line": 35.5,
      "yellow_line": 34.23,
      "day_J": 1.37,
      "day_date": "20260528",
      "trend_ok": true,
      "backtest_win_rate": 100.0,
      "backtest_avg_return": 13.71,
      "backtest_trades": 1
    },
    {
      "ts_code": "300347.SZ",
      "name": "泰格医药",
      "theme_category": "生物医药与器械",
      "week": "2026-W22",
      "week_date": "20260528",
      "week_J": -62.75,
      "week_K": -47.64,
      "week_D": -40.08,
      "white_line": 52.35,
      "yellow_line": 52.33,
      "day_J": 4.88,
      "day_date": "20260528",
      "trend_ok": true,
      "backtest_win_rate": 100.0,
      "backtest_avg_return": 11.74,
      "backtest_trades": 1
    },
    {
      "ts_code": "688321.SH",
      "name": "微芯生物",
      "theme_category": "生物医药",
      "week": "2026-W22",
      "week_date": "20260528",
      "week_J": -129.76,
      "week_K": -82.88,
      "week_D": -59.44,
      "white_line": 29.44,
      "yellow_line": 27.4,
      "day_J": 6.84,
      "day_date": "20260528",
      "trend_ok": true,
      "backtest_win_rate": 100.0,
      "backtest_avg_return": 10.11,
      "backtest_trades": 1
    },
    {
      "ts_code": "688176.SH",
      "name": "亚虹医药-U",
      "theme_category": "生物医药",
      "week": "2026-W22",
      "week_date": "20260528",
      "week_J": -135.73,
      "week_K": -66.38,
      "week_D": -31.7,
      "white_line": 12.49,
      "yellow_line": 10.94,
      "day_J": 1.45,
      "day_date": "20260528",
      "trend_ok": true,
      "backtest_win_rate": 100.0,
      "backtest_avg_return": 9.5,
      "backtest_trades": 1
    },
    {
      "ts_code": "000990.SZ",
      "name": "诚志股份",
      "theme_category": "化工/材料",
      "week": "2026-W22",
      "week_date": "20260527",
      "week_J": -47.02,
      "week_K": 0.27,
      "week_D": 23.92,
      "white_line": 9.52,
      "yellow_line": 8.59,
      "day_J": 9.52,
      "day_date": "20260527",
      "trend_ok": true,
      "backtest_win_rate": 100.0,
      "backtest_avg_return": 9.39,
      "backtest_trades": 1
    },
    {
      "ts_code": "688070.SH",
      "name": "纵横股份",
      "theme_category": "商业航天与低空",
      "week": "2026-W22",
      "week_date": "20260528",
      "week_J": -263.06,
      "week_K": -134.31,
      "week_D": -69.93,
      "white_line": 48.34,
      "yellow_line": 46.71,
      "day_J": 2.72,
      "day_date": "20260528",
      "trend_ok": true,
      "backtest_win_rate": 100.0,
      "backtest_avg_return": 7.83,
      "backtest_trades": 1
    },
    {
      "ts_code": "300455.SZ",
      "name": "航天智装",
      "theme_category": "商业航天与低空",
      "week": "2026-W22",
      "week_date": "20260528",
      "week_J": -17.13,
      "week_K": 0.94,
      "week_D": 9.98,
      "white_line": 24.65,
      "yellow_line": 21.3,
      "day_J": 4.08,
      "day_date": "20260528",
      "trend_ok": true,
      "backtest_win_rate": 100.0,
      "backtest_avg_return": 7.28,
      "backtest_trades": 1
    },
    {
      "ts_code": "688311.SH",
      "name": "盟升电子",
      "theme_category": "集成电路",
      "week": "2026-W22",
      "week_date": "20260528",
      "week_J": -96.78,
      "week_K": -70.57,
      "week_D": -57.46,
      "white_line": 36.93,
      "yellow_line": 35.51,
      "day_J": 10.97,
      "day_date": "20260528",
      "trend_ok": true,
      "backtest_win_rate": 100.0,
      "backtest_avg_return": 6.73,
      "backtest_trades": 1
    },
    {
      "ts_code": "002151.SZ",
      "name": "北斗星通",
      "theme_category": "商业航天与低空",
      "week": "2026-W22",
      "week_date": "20260527",
      "week_J": -20.22,
      "week_K": -8.85,
      "week_D": -3.16,
      "white_line": 38.78,
      "yellow_line": 34.77,
      "day_J": 0.56,
      "day_date": "20260527",
      "trend_ok": true,
      "backtest_win_rate": 100.0,
      "backtest_avg_return": 6.15,
      "backtest_trades": 1
    },
    {
      "ts_code": "600267.SH",
      "name": "海正药业",
      "theme_category": "生物医药",
      "week": "2026-W22",
      "week_date": "20260528",
      "week_J": -37.17,
      "week_K": -0.37,
      "week_D": 18.03,
      "white_line": 10.42,
      "yellow_line": 9.95,
      "day_J": 1.53,
      "day_date": "20260528",
      "trend_ok": true,
      "backtest_win_rate": 100.0,
      "backtest_avg_return": 5.93,
      "backtest_trades": 1
    },
    {
      "ts_code": "600216.SH",
      "name": "浙江医药",
      "theme_category": "生物医药",
      "week": "2026-W22",
      "week_date": "20260528",
      "week_J": -56.53,
      "week_K": -31.48,
      "week_D": -18.96,
      "white_line": 14.64,
      "yellow_line": 14.27,
      "day_J": 2.41,
      "day_date": "20260528",
      "trend_ok": true,
      "backtest_win_rate": 100.0,
      "backtest_avg_return": 2.82,
      "backtest_trades": 1
    },
    {
      "ts_code": "600288.SH",
      "name": "大恒科技",
      "theme_category": "国产软件与信创",
      "week": "2026-W22",
      "week_date": "20260528",
      "week_J": -99.28,
      "week_K": -45.15,
      "week_D": -18.08,
      "white_line": 14.53,
      "yellow_line": 13.1,
      "day_J": 14.4,
      "day_date": "20260528",
      "trend_ok": true,
      "backtest_win_rate": 100.0,
      "backtest_avg_return": 2.43,
      "backtest_trades": 1
    },
    {
      "ts_code": "603016.SH",
      "name": "新宏泰",
      "theme_category": "新能源/电力设备",
      "week": "2026-W22",
      "week_date": "20260528",
      "week_J": -14.66,
      "week_K": 27.35,
      "week_D": 48.36,
      "white_line": 39.85,
      "yellow_line": 33.37,
      "day_J": 12.12,
      "day_date": "20260528",
      "trend_ok": true,
      "backtest_win_rate": 100.0,
      "backtest_avg_return": 1.69,
      "backtest_trades": 1
    },
    {
      "ts_code": "002366.SZ",
      "name": "融发核电",
      "theme_category": "核电",
      "week": "2026-W22",
      "week_date": "20260527",
      "week_J": -157.17,
      "week_K": -80.26,
      "week_D": -41.8,
      "white_line": 7.31,
      "yellow_line": 6.87,
      "day_J": 2.9,
      "day_date": "20260527",
      "trend_ok": true,
      "backtest_win_rate": null,
      "backtest_avg_return": null,
      "backtest_trades": null
    },
    {
      "ts_code": "002389.SZ",
      "name": "航天彩虹",
      "theme_category": "商业航天与低空",
      "week": "2026-W22",
      "week_date": "20260527",
      "week_J": -137.02,
      "week_K": -71.4,
      "week_D": -38.59,
      "white_line": 21.84,
      "yellow_line": 21.21,
      "day_J": 0.71,
      "day_date": "20260527",
      "trend_ok": true,
      "backtest_win_rate": null,
      "backtest_avg_return": null,
      "backtest_trades": null
    },
    {
      "ts_code": "002437.SZ",
      "name": "誉衡药业",
      "theme_category": "生物医药",
      "week": "2026-W22",
      "week_date": "20260527",
      "week_J": -31.2,
      "week_K": -20.88,
      "week_D": -15.71,
      "white_line": 3.28,
      "yellow_line": 3.06,
      "day_J": 8.21,
      "day_date": "20260527",
      "trend_ok": true,
      "backtest_win_rate": null,
      "backtest_avg_return": null,
      "backtest_trades": null
    },
    {
      "ts_code": "002549.SZ",
      "name": "凯美特气",
      "theme_category": "半导体零部件",
      "week": "2026-W22",
      "week_date": "20260527",
      "week_J": -230.53,
      "week_K": -166.93,
      "week_D": -135.13,
      "white_line": 18.92,
      "yellow_line": 16.52,
      "day_J": -9.46,
      "day_date": "20260527",
      "trend_ok": true,
      "backtest_win_rate": null,
      "backtest_avg_return": null,
      "backtest_trades": null
    },
    {
      "ts_code": "300016.SZ",
      "name": "北陆药业",
      "theme_category": "生物医药",
      "week": "2026-W22",
      "week_date": "20260528",
      "week_J": -58.35,
      "week_K": -51.18,
      "week_D": -47.59,
      "white_line": 9.27,
      "yellow_line": 8.47,
      "day_J": 12.98,
      "day_date": "20260528",
      "trend_ok": true,
      "backtest_win_rate": null,
      "backtest_avg_return": null,
      "backtest_trades": null
    },
    {
      "ts_code": "300051.SZ",
      "name": "琏升科技",
      "theme_category": "软件与IT服务",
      "week": "2026-W22",
      "week_date": "20260528",
      "week_J": -39.78,
      "week_K": 21.22,
      "week_D": 51.71,
      "white_line": 11.6,
      "yellow_line": 9.49,
      "day_J": -2.5,
      "day_date": "20260528",
      "trend_ok": true,
      "backtest_win_rate": null,
      "backtest_avg_return": null,
      "backtest_trades": null
    },
    {
      "ts_code": "300149.SZ",
      "name": "睿智医药",
      "theme_category": "生物医药",
      "week": "2026-W22",
      "week_date": "20260528",
      "week_J": -36.45,
      "week_K": -26.74,
      "week_D": -21.88,
      "white_line": 9.99,
      "yellow_line": 9.38,
      "day_J": 14.05,
      "day_date": "20260528",
      "trend_ok": true,
      "backtest_win_rate": null,
      "backtest_avg_return": null,
      "backtest_trades": null
    },
    {
      "ts_code": "300158.SZ",
      "name": "振东制药",
      "theme_category": "生物医药",
      "week": "2026-W22",
      "week_date": "20260528",
      "week_J": -78.77,
      "week_K": -89.02,
      "week_D": -94.15,
      "white_line": 5.78,
      "yellow_line": 5.57,
      "day_J": 3.59,
      "day_date": "20260528",
      "trend_ok": true,
      "backtest_win_rate": null,
      "backtest_avg_return": null,
      "backtest_trades": null
    },
    {
      "ts_code": "300204.SZ",
      "name": "舒泰神",
      "theme_category": "生物医药",
      "week": "2026-W22",
      "week_date": "20260528",
      "week_J": -82.58,
      "week_K": -35.63,
      "week_D": -12.15,
      "white_line": 26.51,
      "yellow_line": 24.95,
      "day_J": 7.6,
      "day_date": "20260528",
      "trend_ok": true,
      "backtest_win_rate": null,
      "backtest_avg_return": null,
      "backtest_trades": null
    },
    {
      "ts_code": "300255.SZ",
      "name": "常山药业",
      "theme_category": "生物医药",
      "week": "2026-W22",
      "week_date": "20260528",
      "week_J": -36.61,
      "week_K": -7.4,
      "week_D": 7.2,
      "white_line": 42.38,
      "yellow_line": 39.85,
      "day_J": 10.01,
      "day_date": "20260528",
      "trend_ok": true,
      "backtest_win_rate": null,
      "backtest_avg_return": null,
      "backtest_trades": null
    },
    {
      "ts_code": "300759.SZ",
      "name": "康龙化成",
      "theme_category": "生物医药与器械",
      "week": "2026-W22",
      "week_date": "20260528",
      "week_J": -29.48,
      "week_K": -3.92,
      "week_D": 8.86,
      "white_line": 27.82,
      "yellow_line": 27.0,
      "day_J": 7.32,
      "day_date": "20260528",
      "trend_ok": true,
      "backtest_win_rate": null,
      "backtest_avg_return": null,
      "backtest_trades": null
    },
    {
      "ts_code": "301155.SZ",
      "name": "海力风电",
      "theme_category": "新能源(光风储电)",
      "week": "2026-W22",
      "week_date": "20260528",
      "week_J": 11.91,
      "week_K": -5.22,
      "week_D": -13.79,
      "white_line": 68.23,
      "yellow_line": 67.8,
      "day_J": 6.24,
      "day_date": "20260528",
      "trend_ok": true,
      "backtest_win_rate": null,
      "backtest_avg_return": null,
      "backtest_trades": null
    },
    {
      "ts_code": "301196.SZ",
      "name": "唯科科技",
      "theme_category": "工业设备/通用机械",
      "week": "2026-W22",
      "week_date": "20260528",
      "week_J": -1059.75,
      "week_K": 212.08,
      "week_D": 848.0,
      "white_line": 98.37,
      "yellow_line": 82.08,
      "day_J": -3.2,
      "day_date": "20260528",
      "trend_ok": true,
      "backtest_win_rate": null,
      "backtest_avg_return": null,
      "backtest_trades": null
    },
    {
      "ts_code": "600210.SH",
      "name": "紫江企业",
      "theme_category": "新能源(光风储电)",
      "week": "2026-W22",
      "week_date": "20260528",
      "week_J": -123.62,
      "week_K": -77.24,
      "week_D": -54.05,
      "white_line": 6.96,
      "yellow_line": 6.74,
      "day_J": 10.45,
      "day_date": "20260528",
      "trend_ok": true,
      "backtest_win_rate": null,
      "backtest_avg_return": null,
      "backtest_trades": null
    },
    {
      "ts_code": "600276.SH",
      "name": "恒瑞医药",
      "theme_category": "生物医药",
      "week": "2026-W22",
      "week_date": "20260528",
      "week_J": -104.01,
      "week_K": -86.56,
      "week_D": -77.83,
      "white_line": 54.36,
      "yellow_line": 54.09,
      "day_J": 7.75,
      "day_date": "20260528",
      "trend_ok": true,
      "backtest_win_rate": null,
      "backtest_avg_return": null,
      "backtest_trades": null
    },
    {
      "ts_code": "600867.SH",
      "name": "通化东宝",
      "theme_category": "生物医药",
      "week": "2026-W22",
      "week_date": "20260528",
      "week_J": -16.78,
      "week_K": -14.39,
      "week_D": -13.2,
      "white_line": 8.83,
      "yellow_line": 8.47,
      "day_J": 8.95,
      "day_date": "20260528",
      "trend_ok": true,
      "backtest_win_rate": null,
      "backtest_avg_return": null,
      "backtest_trades": null
    },
    {
      "ts_code": "601012.SH",
      "name": "隆基绿能",
      "theme_category": "新能源(光风储电)",
      "week": "2026-W22",
      "week_date": "20260528",
      "week_J": -23.49,
      "week_K": -39.91,
      "week_D": -48.12,
      "white_line": 16.89,
      "yellow_line": 16.74,
      "day_J": 8.31,
      "day_date": "20260528",
      "trend_ok": true,
      "backtest_win_rate": null,
      "backtest_avg_return": null,
      "backtest_trades": null
    },
    {
      "ts_code": "603912.SH",
      "name": "603912.SH",
      "theme_category": "未分类",
      "week": "2026-W22",
      "week_date": "20260528",
      "week_J": -16.28,
      "week_K": 14.82,
      "week_D": 30.37,
      "white_line": 9.48,
      "yellow_line": 8.86,
      "day_J": 0.14,
      "day_date": "20260528",
      "trend_ok": true,
      "backtest_win_rate": null,
      "backtest_avg_return": null,
      "backtest_trades": null
    },
    {
      "ts_code": "603998.SH",
      "name": "方盛制药",
      "theme_category": "生物医药",
      "week": "2026-W22",
      "week_date": "20260528",
      "week_J": -90.48,
      "week_K": -51.88,
      "week_D": -32.58,
      "white_line": 10.88,
      "yellow_line": 10.71,
      "day_J": 12.12,
      "day_date": "20260528",
      "trend_ok": true,
      "backtest_win_rate": null,
      "backtest_avg_return": null,
      "backtest_trades": null
    },
    {
      "ts_code": "688106.SH",
      "name": "金宏气体",
      "theme_category": "半导体材料",
      "week": "2026-W22",
      "week_date": "20260528",
      "week_J": -37.22,
      "week_K": 1.13,
      "week_D": 20.31,
      "white_line": 25.51,
      "yellow_line": 22.15,
      "day_J": -1.95,
      "day_date": "20260528",
      "trend_ok": true,
      "backtest_win_rate": null,
      "backtest_avg_return": null,
      "backtest_trades": null
    },
    {
      "ts_code": "688223.SH",
      "name": "晶科能源",
      "theme_category": "新能源(光风储电)",
      "week": "2026-W22",
      "week_date": "20260528",
      "week_J": -82.57,
      "week_K": -44.6,
      "week_D": -25.61,
      "white_line": 6.44,
      "yellow_line": 6.25,
      "day_J": 10.81,
      "day_date": "20260528",
      "trend_ok": true,
      "backtest_win_rate": null,
      "backtest_avg_return": null,
      "backtest_trades": null
    },
    {
      "ts_code": "688235.SH",
      "name": "百济神州",
      "theme_category": "生物医药与器械",
      "week": "2026-W22",
      "week_date": "20260528",
      "week_J": -159.47,
      "week_K": -70.77,
      "week_D": -26.42,
      "white_line": 241.08,
      "yellow_line": 234.71,
      "day_J": 4.44,
      "day_date": "20260528",
      "trend_ok": true,
      "backtest_win_rate": null,
      "backtest_avg_return": null,
      "backtest_trades": null
    },
    {
      "ts_code": "688266.SH",
      "name": "泽璟制药-U",
      "theme_category": "生物医药与器械",
      "week": "2026-W22",
      "week_date": "20260528",
      "week_J": -544.01,
      "week_K": -222.19,
      "week_D": -61.28,
      "white_line": 91.57,
      "yellow_line": 89.55,
      "day_J": 12.37,
      "day_date": "20260528",
      "trend_ok": true,
      "backtest_win_rate": null,
      "backtest_avg_return": null,
      "backtest_trades": null
    },
    {
      "ts_code": "688316.SH",
      "name": "青云科技-U",
      "theme_category": "国产软件与信创",
      "week": "2026-W22",
      "week_date": "20260528",
      "week_J": -181.0,
      "week_K": -99.4,
      "week_D": -58.6,
      "white_line": 69.02,
      "yellow_line": 63.01,
      "day_J": 0.56,
      "day_date": "20260528",
      "trend_ok": true,
      "backtest_win_rate": null,
      "backtest_avg_return": null,
      "backtest_trades": null
    },
    {
      "ts_code": "688339.SH",
      "name": "亿华通-U",
      "theme_category": "氢能",
      "week": "2026-W22",
      "week_date": "20260528",
      "week_J": -66.08,
      "week_K": -34.9,
      "week_D": -19.31,
      "white_line": 26.15,
      "yellow_line": 25.58,
      "day_J": 8.42,
      "day_date": "20260528",
      "trend_ok": true,
      "backtest_win_rate": null,
      "backtest_avg_return": null,
      "backtest_trades": null
    },
    {
      "ts_code": "688356.SH",
      "name": "键凯科技",
      "theme_category": "生物医药",
      "week": "2026-W22",
      "week_date": "20260528",
      "week_J": -42.73,
      "week_K": -19.59,
      "week_D": -8.01,
      "white_line": 92.21,
      "yellow_line": 84.19,
      "day_J": 9.68,
      "day_date": "20260528",
      "trend_ok": true,
      "backtest_win_rate": null,
      "backtest_avg_return": null,
      "backtest_trades": null
    },
    {
      "ts_code": "688506.SH",
      "name": "百利天恒",
      "theme_category": "生物医药与器械",
      "week": "2026-W22",
      "week_date": "20260528",
      "week_J": -59.28,
      "week_K": -35.72,
      "week_D": -23.95,
      "white_line": 272.63,
      "yellow_line": 271.17,
      "day_J": 8.23,
      "day_date": "20260528",
      "trend_ok": true,
      "backtest_win_rate": null,
      "backtest_avg_return": null,
      "backtest_trades": null
    },
    {
      "ts_code": "688566.SH",
      "name": "吉贝尔",
      "theme_category": "生物医药",
      "week": "2026-W22",
      "week_date": "20260528",
      "week_J": -48.6,
      "week_K": -27.94,
      "week_D": -17.61,
      "white_line": 28.46,
      "yellow_line": 27.79,
      "day_J": 14.29,
      "day_date": "20260528",
      "trend_ok": true,
      "backtest_win_rate": null,
      "backtest_avg_return": null,
      "backtest_trades": null
    },
    {
      "ts_code": "688578.SH",
      "name": "艾力斯",
      "theme_category": "生物医药",
      "week": "2026-W22",
      "week_date": "20260528",
      "week_J": -180.18,
      "week_K": -179.75,
      "week_D": -179.54,
      "white_line": 93.34,
      "yellow_line": 89.18,
      "day_J": 0.89,
      "day_date": "20260528",
      "trend_ok": true,
      "backtest_win_rate": null,
      "backtest_avg_return": null,
      "backtest_trades": null
    },
    {
      "ts_code": "688166.SH",
      "name": "博瑞医药",
      "theme_category": "消费/医药/传媒",
      "week": "2026-W22",
      "week_date": "20260528",
      "week_J": 3.65,
      "week_K": 29.91,
      "week_D": 43.03,
      "white_line": 51.0,
      "yellow_line": 50.0,
      "day_J": 10.31,
      "day_date": "20260528",
      "trend_ok": true,
      "backtest_win_rate": 0.0,
      "backtest_avg_return": -8.61,
      "backtest_trades": 1
    }
  ],
  "weekly_only": [
    {
      "ts_code": "002792.SZ",
      "name": "通宇通讯",
      "theme_category": "国产软件与信创",
      "week": "2026-W22",
      "week_date": "20260528",
      "week_J": -23.1,
      "week_K": 1.35,
      "week_D": 13.58,
      "white_line": 41.88,
      "yellow_line": 31.98,
      "day_J": 15.07,
      "day_date": "20260528",
      "trend_ok": true,
      "backtest_win_rate": 100.0,
      "backtest_avg_return": 188.07,
      "backtest_trades": 1
    },
    {
      "ts_code": "002733.SZ",
      "name": "雄韬股份",
      "theme_category": "氢能",
      "week": "2026-W22",
      "week_date": "20260528",
      "week_J": -16.23,
      "week_K": 10.45,
      "week_D": 23.79,
      "white_line": 24.59,
      "yellow_line": 21.12,
      "day_J": 118.68,
      "day_date": "20260528",
      "trend_ok": true,
      "backtest_win_rate": 100.0,
      "backtest_avg_return": 95.5,
      "backtest_trades": 1
    },
    {
      "ts_code": "000878.SZ",
      "name": "云南铜业",
      "theme_category": "国产软件与信创",
      "week": "2026-W22",
      "week_date": "20260527",
      "week_J": -53.35,
      "week_K": -29.7,
      "week_D": -17.87,
      "white_line": 18.86,
      "yellow_line": 16.96,
      "day_J": 35.75,
      "day_date": "20260527",
      "trend_ok": true,
      "backtest_win_rate": 100.0,
      "backtest_avg_return": 84.17,
      "backtest_trades": 1
    },
    {
      "ts_code": "300409.SZ",
      "name": "道氏技术",
      "theme_category": "新能源(光风储电)",
      "week": "2026-W22",
      "week_date": "20260528",
      "week_J": -86.01,
      "week_K": -38.22,
      "week_D": -14.33,
      "white_line": 25.48,
      "yellow_line": 22.0,
      "day_J": 27.02,
      "day_date": "20260528",
      "trend_ok": true,
      "backtest_win_rate": 100.0,
      "backtest_avg_return": 79.76,
      "backtest_trades": 1
    },
    {
      "ts_code": "688131.SH",
      "name": "皓元医药",
      "theme_category": "生物医药",
      "week": "2026-W22",
      "week_date": "20260528",
      "week_J": -70.57,
      "week_K": -20.18,
      "week_D": 5.02,
      "white_line": 68.96,
      "yellow_line": 61.51,
      "day_J": 75.77,
      "day_date": "20260528",
      "trend_ok": true,
      "backtest_win_rate": 100.0,
      "backtest_avg_return": 78.88,
      "backtest_trades": 2
    },
    {
      "ts_code": "301310.SZ",
      "name": "鑫宏业",
      "theme_category": "新能源/电力设备",
      "week": "2026-W22",
      "week_date": "20260528",
      "week_J": -3.07,
      "week_K": 22.02,
      "week_D": 34.56,
      "white_line": 31.17,
      "yellow_line": 27.95,
      "day_J": 92.43,
      "day_date": "20260528",
      "trend_ok": true,
      "backtest_win_rate": 100.0,
      "backtest_avg_return": 74.48,
      "backtest_trades": 1
    },
    {
      "ts_code": "300450.SZ",
      "name": "先导智能",
      "theme_category": "新能源(光风储电)",
      "week": "2026-W22",
      "week_date": "20260528",
      "week_J": -19.47,
      "week_K": 5.4,
      "week_D": 17.84,
      "white_line": 50.75,
      "yellow_line": 42.96,
      "day_J": 36.85,
      "day_date": "20260528",
      "trend_ok": true,
      "backtest_win_rate": 100.0,
      "backtest_avg_return": 50.42,
      "backtest_trades": 2
    },
    {
      "ts_code": "601611.SH",
      "name": "中国核建",
      "theme_category": "核电",
      "week": "2026-W22",
      "week_date": "20260528",
      "week_J": -116.06,
      "week_K": -63.21,
      "week_D": -36.78,
      "white_line": 13.68,
      "yellow_line": 12.05,
      "day_J": 44.86,
      "day_date": "20260528",
      "trend_ok": true,
      "backtest_win_rate": 100.0,
      "backtest_avg_return": 45.93,
      "backtest_trades": 1
    },
    {
      "ts_code": "002432.SZ",
      "name": "九安医疗",
      "theme_category": "生物医药与器械",
      "week": "2026-W22",
      "week_date": "20260527",
      "week_J": -12.21,
      "week_K": 21.7,
      "week_D": 38.66,
      "white_line": 60.82,
      "yellow_line": 51.2,
      "day_J": 91.38,
      "day_date": "20260527",
      "trend_ok": true,
      "backtest_win_rate": 100.0,
      "backtest_avg_return": 43.88,
      "backtest_trades": 2
    },
    {
      "ts_code": "603659.SH",
      "name": "璞泰来",
      "theme_category": "新能源(光风储电)",
      "week": "2026-W22",
      "week_date": "20260528",
      "week_J": -76.51,
      "week_K": -22.04,
      "week_D": 5.19,
      "white_line": 29.99,
      "yellow_line": 25.62,
      "day_J": 24.73,
      "day_date": "20260528",
      "trend_ok": true,
      "backtest_win_rate": 100.0,
      "backtest_avg_return": 38.58,
      "backtest_trades": 1
    },
    {
      "ts_code": "600510.SH",
      "name": "黑牡丹",
      "theme_category": "地产/基建",
      "week": "2026-W22",
      "week_date": "20260528",
      "week_J": 9.31,
      "week_K": 15.98,
      "week_D": 19.32,
      "white_line": 8.86,
      "yellow_line": 7.71,
      "day_J": 19.46,
      "day_date": "20260528",
      "trend_ok": true,
      "backtest_win_rate": 100.0,
      "backtest_avg_return": 36.53,
      "backtest_trades": 2
    },
    {
      "ts_code": "002603.SZ",
      "name": "以岭药业",
      "theme_category": "生物医药",
      "week": "2026-W22",
      "week_date": "20260527",
      "week_J": -92.12,
      "week_K": -47.24,
      "week_D": -24.8,
      "white_line": 16.53,
      "yellow_line": 16.23,
      "day_J": 49.17,
      "day_date": "20260527",
      "trend_ok": true,
      "backtest_win_rate": 100.0,
      "backtest_avg_return": 35.46,
      "backtest_trades": 1
    },
    {
      "ts_code": "002497.SZ",
      "name": "雅化集团",
      "theme_category": "化工/材料",
      "week": "2026-W22",
      "week_date": "20260527",
      "week_J": 5.59,
      "week_K": 7.75,
      "week_D": 8.82,
      "white_line": 24.07,
      "yellow_line": 19.95,
      "day_J": 22.42,
      "day_date": "20260527",
      "trend_ok": true,
      "backtest_win_rate": 100.0,
      "backtest_avg_return": 35.16,
      "backtest_trades": 2
    },
    {
      "ts_code": "603259.SH",
      "name": "药明康德",
      "theme_category": "生物医药与器械",
      "week": "2026-W22",
      "week_date": "20260528",
      "week_J": 6.54,
      "week_K": 19.94,
      "week_D": 26.64,
      "white_line": 96.49,
      "yellow_line": 86.22,
      "day_J": 18.52,
      "day_date": "20260528",
      "trend_ok": true,
      "backtest_win_rate": 100.0,
      "backtest_avg_return": 31.98,
      "backtest_trades": 1
    },
    {
      "ts_code": "688295.SH",
      "name": "中复神鹰",
      "theme_category": "新材料",
      "week": "2026-W22",
      "week_date": "20260528",
      "week_J": -70.07,
      "week_K": 2.39,
      "week_D": 38.62,
      "white_line": 44.29,
      "yellow_line": 34.71,
      "day_J": 23.09,
      "day_date": "20260528",
      "trend_ok": true,
      "backtest_win_rate": 100.0,
      "backtest_avg_return": 31.59,
      "backtest_trades": 2
    },
    {
      "ts_code": "688607.SH",
      "name": "康众医疗",
      "theme_category": "生物医药与器械",
      "week": "2026-W22",
      "week_date": "20260528",
      "week_J": -218.53,
      "week_K": -66.65,
      "week_D": 9.3,
      "white_line": 55.18,
      "yellow_line": 41.54,
      "day_J": 22.49,
      "day_date": "20260528",
      "trend_ok": true,
      "backtest_win_rate": 100.0,
      "backtest_avg_return": 30.32,
      "backtest_trades": 1
    },
    {
      "ts_code": "600348.SH",
      "name": "华阳股份",
      "theme_category": "新能源(光风储电)",
      "week": "2026-W22",
      "week_date": "20260528",
      "week_J": -38.45,
      "week_K": -17.33,
      "week_D": -6.77,
      "white_line": 9.08,
      "yellow_line": 8.31,
      "day_J": 44.15,
      "day_date": "20260528",
      "trend_ok": true,
      "backtest_win_rate": 100.0,
      "backtest_avg_return": 29.69,
      "backtest_trades": 1
    },
    {
      "ts_code": "300342.SZ",
      "name": "天银机电",
      "theme_category": "国产软件与信创",
      "week": "2026-W22",
      "week_date": "20260528",
      "week_J": -42.39,
      "week_K": 11.7,
      "week_D": 38.74,
      "white_line": 48.52,
      "yellow_line": 35.43,
      "day_J": 18.76,
      "day_date": "20260528",
      "trend_ok": true,
      "backtest_win_rate": 100.0,
      "backtest_avg_return": 25.36,
      "backtest_trades": 1
    },
    {
      "ts_code": "600468.SH",
      "name": "百利电气",
      "theme_category": "可控核聚变",
      "week": "2026-W22",
      "week_date": "20260528",
      "week_J": -46.39,
      "week_K": -28.39,
      "week_D": -19.39,
      "white_line": 7.4,
      "yellow_line": 6.71,
      "day_J": 16.18,
      "day_date": "20260528",
      "trend_ok": true,
      "backtest_win_rate": 100.0,
      "backtest_avg_return": 24.66,
      "backtest_trades": 1
    },
    {
      "ts_code": "300184.SZ",
      "name": "力源信息",
      "theme_category": "消费电子/元器件",
      "week": "2026-W22",
      "week_date": "20260528",
      "week_J": -151.33,
      "week_K": 153.35,
      "week_D": 305.69,
      "white_line": 11.6,
      "yellow_line": 10.6,
      "day_J": 76.56,
      "day_date": "20260528",
      "trend_ok": true,
      "backtest_win_rate": 100.0,
      "backtest_avg_return": 24.22,
      "backtest_trades": 2
    },
    {
      "ts_code": "300750.SZ",
      "name": "宁德时代",
      "theme_category": "新能源(光风储电)",
      "week": "2026-W22",
      "week_date": "20260528",
      "week_J": -34.72,
      "week_K": 11.27,
      "week_D": 34.27,
      "white_line": 385.39,
      "yellow_line": 338.82,
      "day_J": 54.9,
      "day_date": "20260528",
      "trend_ok": true,
      "backtest_win_rate": 100.0,
      "backtest_avg_return": 23.6,
      "backtest_trades": 2
    },
    {
      "ts_code": "002653.SZ",
      "name": "海思科",
      "theme_category": "生物医药",
      "week": "2026-W22",
      "week_date": "20260528",
      "week_J": -55.14,
      "week_K": -10.74,
      "week_D": 11.46,
      "white_line": 50.88,
      "yellow_line": 47.5,
      "day_J": 22.34,
      "day_date": "20260528",
      "trend_ok": true,
      "backtest_win_rate": 100.0,
      "backtest_avg_return": 19.59,
      "backtest_trades": 3
    },
    {
      "ts_code": "600316.SH",
      "name": "洪都航空",
      "theme_category": "商业航天与低空",
      "week": "2026-W22",
      "week_date": "20260528",
      "week_J": -64.91,
      "week_K": -66.23,
      "week_D": -66.89,
      "white_line": 36.07,
      "yellow_line": 34.17,
      "day_J": 18.66,
      "day_date": "20260528",
      "trend_ok": true,
      "backtest_win_rate": 100.0,
      "backtest_avg_return": 11.31,
      "backtest_trades": 1
    },
    {
      "ts_code": "002826.SZ",
      "name": "易明医药",
      "theme_category": "生物医药与器械",
      "week": "2026-W22",
      "week_date": "20260528",
      "week_J": -153.84,
      "week_K": -103.89,
      "week_D": -78.92,
      "white_line": 19.05,
      "yellow_line": 17.37,
      "day_J": 29.04,
      "day_date": "20260528",
      "trend_ok": true,
      "backtest_win_rate": 100.0,
      "backtest_avg_return": 11.13,
      "backtest_trades": 1
    },
    {
      "ts_code": "688488.SH",
      "name": "艾迪药业",
      "theme_category": "生物医药",
      "week": "2026-W22",
      "week_date": "20260528",
      "week_J": -51.89,
      "week_K": -14.31,
      "week_D": 4.47,
      "white_line": 16.09,
      "yellow_line": 14.56,
      "day_J": 39.49,
      "day_date": "20260528",
      "trend_ok": true,
      "backtest_win_rate": 100.0,
      "backtest_avg_return": 10.64,
      "backtest_trades": 1
    },
    {
      "ts_code": "000881.SZ",
      "name": "中广核技",
      "theme_category": "核电",
      "week": "2026-W22",
      "week_date": "20260527",
      "week_J": -86.76,
      "week_K": -52.1,
      "week_D": -34.78,
      "white_line": 7.77,
      "yellow_line": 7.69,
      "day_J": 15.79,
      "day_date": "20260527",
      "trend_ok": true,
      "backtest_win_rate": 100.0,
      "backtest_avg_return": 3.71,
      "backtest_trades": 1
    },
    {
      "ts_code": "688027.SH",
      "name": "国盾量子",
      "theme_category": "量子信息",
      "week": "2026-W22",
      "week_date": "20260528",
      "week_J": -4.09,
      "week_K": -4.5,
      "week_D": -4.7,
      "white_line": 554.0,
      "yellow_line": 456.91,
      "day_J": 49.99,
      "day_date": "20260528",
      "trend_ok": true,
      "backtest_win_rate": 100.0,
      "backtest_avg_return": 3.63,
      "backtest_trades": 1
    },
    {
      "ts_code": "300520.SZ",
      "name": "科大国创",
      "theme_category": "量子信息",
      "week": "2026-W22",
      "week_date": "20260528",
      "week_J": 6.54,
      "week_K": -0.37,
      "week_D": -3.82,
      "white_line": 36.2,
      "yellow_line": 32.09,
      "day_J": 55.72,
      "day_date": "20260528",
      "trend_ok": true,
      "backtest_win_rate": 100.0,
      "backtest_avg_return": 1.65,
      "backtest_trades": 1
    },
    {
      "ts_code": "002025.SZ",
      "name": "航天电器",
      "theme_category": "商业航天与低空",
      "week": "2026-W22",
      "week_date": "20260527",
      "week_J": -14.82,
      "week_K": 20.71,
      "week_D": 38.47,
      "white_line": 60.64,
      "yellow_line": 54.22,
      "day_J": 40.43,
      "day_date": "20260527",
      "trend_ok": true,
      "backtest_win_rate": 50.0,
      "backtest_avg_return": 25.14,
      "backtest_trades": 2
    },
    {
      "ts_code": "300627.SZ",
      "name": "华测导航",
      "theme_category": "商业航天与低空",
      "week": "2026-W22",
      "week_date": "20260528",
      "week_J": -97.89,
      "week_K": -61.08,
      "week_D": -42.68,
      "white_line": 32.34,
      "yellow_line": 31.15,
      "day_J": 15.9,
      "day_date": "20260528",
      "trend_ok": true,
      "backtest_win_rate": 50.0,
      "backtest_avg_return": 3.38,
      "backtest_trades": 2
    },
    {
      "ts_code": "300207.SZ",
      "name": "欣旺达",
      "theme_category": "新能源(光风储电)",
      "week": "2026-W22",
      "week_date": "20260528",
      "week_J": -67.2,
      "week_K": -46.9,
      "week_D": -36.75,
      "white_line": 25.35,
      "yellow_line": 24.09,
      "day_J": 21.33,
      "day_date": "20260528",
      "trend_ok": true,
      "backtest_win_rate": 50.0,
      "backtest_avg_return": 0.9,
      "backtest_trades": 2
    },
    {
      "ts_code": "000555.SZ",
      "name": "神州信息",
      "theme_category": "量子信息",
      "week": "2026-W22",
      "week_date": "20260527",
      "week_J": -75.49,
      "week_K": -56.83,
      "week_D": -47.49,
      "white_line": 15.0,
      "yellow_line": 14.28,
      "day_J": 26.81,
      "day_date": "20260527",
      "trend_ok": true,
      "backtest_win_rate": null,
      "backtest_avg_return": null,
      "backtest_trades": null
    },
    {
      "ts_code": "002243.SZ",
      "name": "力合科创",
      "theme_category": "国产软件与信创",
      "week": "2026-W22",
      "week_date": "20260527",
      "week_J": -173.99,
      "week_K": -91.95,
      "week_D": -50.93,
      "white_line": 9.0,
      "yellow_line": 8.67,
      "day_J": 30.45,
      "day_date": "20260527",
      "trend_ok": true,
      "backtest_win_rate": null,
      "backtest_avg_return": null,
      "backtest_trades": null
    },
    {
      "ts_code": "002812.SZ",
      "name": "恩捷股份",
      "theme_category": "新能源(光风储电)",
      "week": "2026-W22",
      "week_date": "20260528",
      "week_J": -24.03,
      "week_K": 16.9,
      "week_D": 37.36,
      "white_line": 64.3,
      "yellow_line": 52.31,
      "day_J": 29.38,
      "day_date": "20260528",
      "trend_ok": true,
      "backtest_win_rate": null,
      "backtest_avg_return": null,
      "backtest_trades": null
    },
    {
      "ts_code": "002866.SZ",
      "name": "传艺科技",
      "theme_category": "消费电子/元器件",
      "week": "2026-W22",
      "week_date": "20260528",
      "week_J": -28.75,
      "week_K": 10.91,
      "week_D": 30.74,
      "white_line": 20.81,
      "yellow_line": 18.87,
      "day_J": 15.61,
      "day_date": "20260528",
      "trend_ok": true,
      "backtest_win_rate": null,
      "backtest_avg_return": null,
      "backtest_trades": null
    },
    {
      "ts_code": "300758.SZ",
      "name": "七彩化学",
      "theme_category": "新能源(光风储电)",
      "week": "2026-W22",
      "week_date": "20260528",
      "week_J": -17.0,
      "week_K": -12.28,
      "week_D": -9.91,
      "white_line": 13.87,
      "yellow_line": 13.59,
      "day_J": 37.62,
      "day_date": "20260528",
      "trend_ok": true,
      "backtest_win_rate": null,
      "backtest_avg_return": null,
      "backtest_trades": null
    },
    {
      "ts_code": "301232.SZ",
      "name": "飞沃科技",
      "theme_category": "新能源/电力设备",
      "week": "2026-W22",
      "week_date": "20260528",
      "week_J": 14.62,
      "week_K": 28.91,
      "week_D": 36.05,
      "white_line": 123.64,
      "yellow_line": 85.54,
      "day_J": 34.64,
      "day_date": "20260528",
      "trend_ok": true,
      "backtest_win_rate": null,
      "backtest_avg_return": null,
      "backtest_trades": null
    },
    {
      "ts_code": "600875.SH",
      "name": "东方电气",
      "theme_category": "核电",
      "week": "2026-W22",
      "week_date": "20260528",
      "week_J": -102.94,
      "week_K": -44.04,
      "week_D": -14.59,
      "white_line": 33.84,
      "yellow_line": 27.18,
      "day_J": 19.57,
      "day_date": "20260528",
      "trend_ok": true,
      "backtest_win_rate": null,
      "backtest_avg_return": null,
      "backtest_trades": null
    },
    {
      "ts_code": "603308.SH",
      "name": "应流股份",
      "theme_category": "核电",
      "week": "2026-W22",
      "week_date": "20260528",
      "week_J": 13.64,
      "week_K": 35.14,
      "week_D": 45.88,
      "white_line": 61.53,
      "yellow_line": 46.41,
      "day_J": 27.02,
      "day_date": "20260528",
      "trend_ok": true,
      "backtest_win_rate": null,
      "backtest_avg_return": null,
      "backtest_trades": null
    },
    {
      "ts_code": "603590.SH",
      "name": "康辰药业",
      "theme_category": "生物医药",
      "week": "2026-W22",
      "week_date": "20260528",
      "week_J": -115.39,
      "week_K": -74.92,
      "week_D": -54.69,
      "white_line": 37.05,
      "yellow_line": 36.76,
      "day_J": 23.64,
      "day_date": "20260528",
      "trend_ok": true,
      "backtest_win_rate": null,
      "backtest_avg_return": null,
      "backtest_trades": null
    },
    {
      "ts_code": "688122.SH",
      "name": "西部超导",
      "theme_category": "新材料",
      "week": "2026-W22",
      "week_date": "20260528",
      "week_J": -49.09,
      "week_K": -39.87,
      "week_D": -35.26,
      "white_line": 70.15,
      "yellow_line": 63.79,
      "day_J": 101.26,
      "day_date": "20260528",
      "trend_ok": true,
      "backtest_win_rate": null,
      "backtest_avg_return": null,
      "backtest_trades": null
    },
    {
      "ts_code": "688205.SH",
      "name": "688205.SH",
      "theme_category": "未分类",
      "week": "2026-W22",
      "week_date": "20260528",
      "week_J": -60.7,
      "week_K": 8.92,
      "week_D": 43.72,
      "white_line": 192.3,
      "yellow_line": 141.03,
      "day_J": 21.47,
      "day_date": "20260528",
      "trend_ok": true,
      "backtest_win_rate": null,
      "backtest_avg_return": null,
      "backtest_trades": null
    },
    {
      "ts_code": "688229.SH",
      "name": "博睿数据",
      "theme_category": "国产软件与信创",
      "week": "2026-W22",
      "week_date": "20260528",
      "week_J": -58.71,
      "week_K": -48.02,
      "week_D": -42.68,
      "white_line": 79.91,
      "yellow_line": 67.99,
      "day_J": 16.45,
      "day_date": "20260528",
      "trend_ok": true,
      "backtest_win_rate": null,
      "backtest_avg_return": null,
      "backtest_trades": null
    },
    {
      "ts_code": "688297.SH",
      "name": "中无人机",
      "theme_category": "商业航天与低空",
      "week": "2026-W22",
      "week_date": "20260528",
      "week_J": -69.84,
      "week_K": -39.17,
      "week_D": -23.83,
      "white_line": 46.89,
      "yellow_line": 45.53,
      "day_J": 37.47,
      "day_date": "20260528",
      "trend_ok": true,
      "backtest_win_rate": null,
      "backtest_avg_return": null,
      "backtest_trades": null
    },
    {
      "ts_code": "688333.SH",
      "name": "688333.SH",
      "theme_category": "未分类",
      "week": "2026-W22",
      "week_date": "20260528",
      "week_J": -4.53,
      "week_K": -12.77,
      "week_D": -16.9,
      "white_line": 89.65,
      "yellow_line": 79.87,
      "day_J": 107.63,
      "day_date": "20260528",
      "trend_ok": true,
      "backtest_win_rate": null,
      "backtest_avg_return": null,
      "backtest_trades": null
    },
    {
      "ts_code": "002422.SZ",
      "name": "科伦药业",
      "theme_category": "生物医药",
      "week": "2026-W22",
      "week_date": "20260527",
      "week_J": -165.93,
      "week_K": -108.53,
      "week_D": -79.83,
      "white_line": 31.69,
      "yellow_line": 31.56,
      "day_J": 111.74,
      "day_date": "20260527",
      "trend_ok": true,
      "backtest_win_rate": 0.0,
      "backtest_avg_return": -1.01,
      "backtest_trades": 1
    },
    {
      "ts_code": "603087.SH",
      "name": "甘李药业",
      "theme_category": "生物医药",
      "week": "2026-W22",
      "week_date": "20260528",
      "week_J": -34.98,
      "week_K": -45.91,
      "week_D": -51.37,
      "white_line": 60.55,
      "yellow_line": 58.3,
      "day_J": 25.52,
      "day_date": "20260528",
      "trend_ok": true,
      "backtest_win_rate": 0.0,
      "backtest_avg_return": -1.1,
      "backtest_trades": 1
    }
  ],
  "missed": [
    {
      "ts_code": "002897.SZ",
      "name": "意华股份",
      "theme_category": "国产软件与信创",
      "week": "2026-W22",
      "week_date": "20260528",
      "week_J": 75.15,
      "week_K": 27.28,
      "week_D": 3.35,
      "white_line": 58.97,
      "yellow_line": 51.82,
      "day_J": 73.83,
      "day_date": "20260528",
      "trend_ok": true,
      "backtest_win_rate": 100.0,
      "backtest_avg_return": 22.52,
      "backtest_trades": 2,
      "week_prev_J": -0.37
    },
    {
      "ts_code": "300265.SZ",
      "name": "通光线缆",
      "theme_category": "新能源/电力设备",
      "week": "2026-W22",
      "week_date": "20260528",
      "week_J": 35.7,
      "week_K": -4.89,
      "week_D": -25.18,
      "white_line": 16.62,
      "yellow_line": 13.45,
      "day_J": 8.85,
      "day_date": "20260528",
      "trend_ok": true,
      "backtest_win_rate": 100.0,
      "backtest_avg_return": 16.35,
      "backtest_trades": 2,
      "week_prev_J": 13.99
    },
    {
      "ts_code": "300394.SZ",
      "name": "天孚通信",
      "theme_category": "人工智能(AI算力)",
      "week": "2026-W22",
      "week_date": "20260528",
      "week_J": 28.81,
      "week_K": 2.17,
      "week_D": -11.15,
      "white_line": 287.67,
      "yellow_line": 215.14,
      "day_J": 105.04,
      "day_date": "20260528",
      "trend_ok": true,
      "backtest_win_rate": 100.0,
      "backtest_avg_return": 133.34,
      "backtest_trades": 1,
      "week_prev_J": -31.2
    },
    {
      "ts_code": "300648.SZ",
      "name": "星云股份",
      "theme_category": "国产软件与信创",
      "week": "2026-W22",
      "week_date": "20260528",
      "week_J": 39.11,
      "week_K": 3.85,
      "week_D": -13.79,
      "white_line": 51.15,
      "yellow_line": 44.98,
      "day_J": 58.59,
      "day_date": "20260528",
      "trend_ok": true,
      "backtest_win_rate": null,
      "backtest_avg_return": null,
      "backtest_trades": null,
      "week_prev_J": -12.62
    },
    {
      "ts_code": "301281.SZ",
      "name": "科源制药",
      "theme_category": "生物医药与器械",
      "week": "2026-W22",
      "week_date": "20260528",
      "week_J": 31.33,
      "week_K": 18.3,
      "week_D": 11.79,
      "white_line": 35.84,
      "yellow_line": 33.45,
      "day_J": 84.22,
      "day_date": "20260528",
      "trend_ok": true,
      "backtest_win_rate": 100.0,
      "backtest_avg_return": 10.55,
      "backtest_trades": 1,
      "week_prev_J": -12.97
    },
    {
      "ts_code": "603232.SH",
      "name": "格尔软件",
      "theme_category": "国产软件与信创",
      "week": "2026-W22",
      "week_date": "20260528",
      "week_J": 16.66,
      "week_K": -4.24,
      "week_D": -14.7,
      "white_line": 20.18,
      "yellow_line": 18.61,
      "day_J": 71.21,
      "day_date": "20260528",
      "trend_ok": true,
      "backtest_win_rate": 100.0,
      "backtest_avg_return": 40.7,
      "backtest_trades": 1,
      "week_prev_J": -31.32
    }
  ]
}